prepid/__init__.py
prepid/core.py
prepid/py.typed
prepid-0.0.1.dist-info/METADATA
prepid-0.0.1.dist-info/WHEEL
prepid-0.0.1.dist-info/licenses/LICENSE
prepid-0.0.1.dist-info/RECORD
