Metadata-Version: 2.4
Name: prepid
Version: 0.0.1
Summary: A Python package for fetching and converting currency rates using the Prebid currency file.
Project-URL: Homepage, https://github.com/kokamkarsahil/prepid-py
Project-URL: Bug Tracker, https://github.com/kokamkarsahil/prepid-py/issues
Author-email: Sahil <sahil@kokamkar.com>
License-File: LICENSE
Classifier: Development Status :: 3 - Alpha
Classifier: Intended Audience :: Developers
Classifier: License :: OSI Approved :: MIT License
Classifier: Operating System :: OS Independent
Classifier: Programming Language :: Python :: 3
Classifier: Programming Language :: Python :: 3.8
Classifier: Programming Language :: Python :: 3.9
Classifier: Programming Language :: Python :: 3.10
Classifier: Programming Language :: Python :: 3.11
Classifier: Programming Language :: Python :: 3.12
Classifier: Topic :: Software Development :: Libraries :: Python Modules
Requires-Python: >=3.8
Requires-Dist: appdirs>=1.4.4
Requires-Dist: requests>=2.25.0
Provides-Extra: dev
Requires-Dist: pytest>=8.0; extra == 'dev'
Requires-Dist: requests-mock>=1.9.3; extra == 'dev'
